zqykjhttp/__init__.py
zqykjhttp/example.py
zqykjhttp/webclient.py
zqykjclient-1.0.0.dist-info/METADATA
zqykjclient-1.0.0.dist-info/WHEEL
zqykjclient-1.0.0.dist-info/top_level.txt
zqykjclient-1.0.0.dist-info/RECORD
