Metadata-Version: 2.1
Name: zqykjclient
Version: 1.0.0
Summary: lbsys
Home-page: https://github.com/yourusername/mypackage
Author: cxx
Author-email: cuixiaoxiao@zqykj.com
Requires-Python: >=3.6
Requires-Dist: requests>=2.0.0
